sovereign/__init__.py
sovereign/app.py
sovereign/constants.py
sovereign/context.py
sovereign/discovery.py
sovereign/dynamic_config/__init__.py
sovereign/dynamic_config/deser.py
sovereign/dynamic_config/loaders.py
sovereign/error_info.py
sovereign/logging/access_logger.py
sovereign/logging/application_logger.py
sovereign/logging/base_logger.py
sovereign/logging/bootstrapper.py
sovereign/logging/types.py
sovereign/middlewares.py
sovereign/modifiers/__init__.py
sovereign/modifiers/lib.py
sovereign/response_class.py
sovereign/schemas.py
sovereign/server.py
sovereign/sources/__init__.py
sovereign/sources/file.py
sovereign/sources/inline.py
sovereign/sources/lib.py
sovereign/sources/poller.py
sovereign/static/panel.js
sovereign/static/sass/style.scss
sovereign/static/search_filter.js
sovereign/static/style.css
sovereign/statistics.py
sovereign/templates/base.html
sovereign/templates/err.html
sovereign/templates/resources.html
sovereign/testing/loaders.py
sovereign/testing/modifiers.py
sovereign/tracing.py
sovereign/utils/__init__.py
sovereign/utils/auth.py
sovereign/utils/crypto/__init__.py
sovereign/utils/crypto/crypto.py
sovereign/utils/crypto/suites/__init__.py
sovereign/utils/crypto/suites/aes_gcm_cipher.py
sovereign/utils/crypto/suites/base_cipher.py
sovereign/utils/crypto/suites/disabled_cipher.py
sovereign/utils/crypto/suites/fernet_cipher.py
sovereign/utils/dictupdate.py
sovereign/utils/eds.py
sovereign/utils/entry_point_loader.py
sovereign/utils/mock.py
sovereign/utils/resources.py
sovereign/utils/templates.py
sovereign/utils/timer.py
sovereign/utils/version_info.py
sovereign/utils/weighted_clusters.py
sovereign/views/__init__.py
sovereign/views/admin.py
sovereign/views/crypto.py
sovereign/views/discovery.py
sovereign/views/healthchecks.py
sovereign/views/interface.py
sovereign-0.32.5.dist-info/LICENSE.txt
sovereign-0.32.5.dist-info/METADATA
sovereign-0.32.5.dist-info/WHEEL
sovereign-0.32.5.dist-info/entry_points.txt
sovereign-0.32.5.dist-info/RECORD
