Metadata-Version: 2.1
Name: sovereign
Version: 0.32.5
Summary: Envoy Proxy control-plane written in Python
Home-page: https://pypi.org/project/sovereign/
License: Apache-2.0
Keywords: envoy,envoyproxy,control-plane,management,server
Author: Vasili Syrakis
Author-email: vsyrakis@atlassian.com
Requires-Python: >=3.11,<4.0
Classifier: Development Status :: 5 - Production/Stable
Classifier: Environment :: No Input/Output (Daemon)
Classifier: Intended Audience :: Developers
Classifier: Intended Audience :: Information Technology
Classifier: Intended Audience :: System Administrators
Classifier: License :: OSI Approved :: Apache Software License
Classifier: Natural Language :: English
Classifier: Operating System :: POSIX :: Linux
Classifier: Programming Language :: Python :: 3
Classifier: Programming Language :: Python :: 3.11
Classifier: Programming Language :: Python :: 3.12
Classifier: Programming Language :: Python :: 3.13
Classifier: Programming Language :: Python :: 3.10
Classifier: Programming Language :: Python :: 3.8
Classifier: Programming Language :: Python :: 3.9
Classifier: Topic :: Internet :: Proxy Servers
Provides-Extra: boto
Provides-Extra: caching
Provides-Extra: httptools
Provides-Extra: orjson
Provides-Extra: sentry
Provides-Extra: statsd
Provides-Extra: ujson
Requires-Dist: Jinja2 (>=3.1.2,<4.0.0)
Requires-Dist: PyYAML (>=6.0.1,<7.0.0)
Requires-Dist: aiofiles (>=23.2.1,<24.0.0)
Requires-Dist: boto3 (>=1.28.62,<2.0.0) ; extra == "boto"
Requires-Dist: cachelib (>=0.10.2,<0.11.0)
Requires-Dist: cachetools (>=5.3.2,<6.0.0)
Requires-Dist: cashews[redis] (>=6.3.0,<7.0.0) ; extra == "caching"
Requires-Dist: croniter (>=1.4.1,<2.0.0)
Requires-Dist: cryptography (>=42.0.0,<43.0.0)
Requires-Dist: datadog (>=0.50.1) ; extra == "statsd"
Requires-Dist: fastapi (>=0.116.0,<0.117.0)
Requires-Dist: glom (>=23.3.0,<24.0.0)
Requires-Dist: gunicorn (>=23.0.0,<24.0.0)
Requires-Dist: h11 (>=0.16.0,<0.17.0)
Requires-Dist: httptools (>=0.6.0,<0.7.0) ; extra == "httptools"
Requires-Dist: orjson (>=3.9.15,<4.0.0) ; extra == "orjson"
Requires-Dist: pydantic (>=2.7.2,<3.0.0)
Requires-Dist: pydantic-settings (<2.6.0)
Requires-Dist: redis (<=5.0.0)
Requires-Dist: requests (>=2.32.4,<3.0.0)
Requires-Dist: sentry-sdk (>=2.14.0,<3.0.0) ; extra == "sentry"
Requires-Dist: starlette (>=0.47.2,<0.48.0)
Requires-Dist: starlette-context (>=0.3.6,<0.4.0)
Requires-Dist: structlog (>=23.1.0,<24.0.0)
Requires-Dist: ujson (>=5.8.0,<6.0.0) ; extra == "ujson"
Requires-Dist: uvicorn (>=0.23.2,<0.24.0)
Requires-Dist: uvloop (>=0.19.0,<0.20.0)
Project-URL: Documentation, https://developer.atlassian.com/platform/sovereign/
Project-URL: Repository, https://bitbucket.org/atlassian/sovereign/src/master/
